enot_prunable_modules/__init__.py
enot_prunable_modules/replace_factory.py
enot_prunable_modules/replace_tools.py
enot_prunable_modules/utils.py
enot_prunable_modules/replace_modules/__init__.py
enot_prunable_modules/replace_modules/replacer.py
enot_prunable_modules/replace_modules/deepfilter/__init__.py
enot_prunable_modules/replace_modules/deepfilter/group_einsum.py
enot_prunable_modules/replace_modules/diffusers/__init__.py
enot_prunable_modules/replace_modules/diffusers/attention.py
enot_prunable_modules/replace_modules/diffusers/downsample.py
enot_prunable_modules/replace_modules/diffusers/feedforward.py
enot_prunable_modules/replace_modules/diffusers/resnet.py
enot_prunable_modules/replace_modules/diffusers/transformer.py
enot_prunable_modules/replace_modules/diffusers/upsample.py
enot_prunable_modules/replace_modules/timm/__init__.py
enot_prunable_modules/replace_modules/timm/levit_attention.py
enot_prunable_modules/replace_modules/timm/timm_attention.py
enot_prunable_modules/replace_modules/torch/__init__.py
enot_prunable_modules/replace_modules/torch/glu.py
enot_prunable_modules/replace_modules/torch/group_conv.py
enot_prunable_modules/replace_modules/torch/group_norm.py
enot_prunable_modules/replace_modules/torchvision/__init__.py
enot_prunable_modules/replace_modules/torchvision/torchvision_attention.py
enot_prunable_modules/replace_modules/transformers/__init__.py
enot_prunable_modules/replace_modules/transformers/gpt2_attention.py
enot_prunable_modules/replace_modules/transformers/gpt_neox_attention.py
enot_prunable_modules/replace_modules/transformers/mistral_attention.py
enot_prunable_modules-1.9.2.dist-info/LICENSE
enot_prunable_modules-1.9.2.dist-info/METADATA
enot_prunable_modules-1.9.2.dist-info/WHEEL
enot_prunable_modules-1.9.2.dist-info/top_level.txt
enot_prunable_modules-1.9.2.dist-info/RECORD
