Metadata-Version: 2.1
Name: enot-prunable-modules
Version: 1.9.2
Summary: Prunable modules for ENOT Framework
Author-email: ENOT LLC <enot@enot.ai>
License: Apache License
Project-URL: homepage, https://enot.ai
Project-URL: documentation, https://enot-autodl.rtd.enot.ai/en/latest/
Keywords: AI,ENOT,Pruning
Classifier: Development Status :: 5 - Production/Stable
Classifier: License :: OSI Approved :: Apache Software License
Classifier: Programming Language :: Python
Classifier: Programming Language :: Python :: 3.8
Classifier: Programming Language :: Python :: 3.9
Classifier: Programming Language :: Python :: 3.10
Classifier: Programming Language :: Python :: 3 :: Only
Requires-Python: >=3.8
License-File: LICENSE
Requires-Dist: torch <2.4.0,>=1.8.0
Provides-Extra: deepfilter
Requires-Dist: deepfilternet ~=0.5.6 ; extra == 'deepfilter'
Requires-Dist: torchaudio ; extra == 'deepfilter'
Provides-Extra: dev
Requires-Dist: black ; extra == 'dev'
Requires-Dist: pylint ; extra == 'dev'
Requires-Dist: pre-commit ; extra == 'dev'
Requires-Dist: isort ; extra == 'dev'
Requires-Dist: pytest ; extra == 'dev'
Requires-Dist: enot-autodl ; extra == 'dev'
Requires-Dist: fvcore ; extra == 'dev'
Requires-Dist: timm <=0.6.13 ; extra == 'dev'
Requires-Dist: diffusers ~=0.24.0 ; extra == 'dev'
Requires-Dist: transformers ~=4.35.2 ; extra == 'dev'
Requires-Dist: deepfilternet ~=0.5.6 ; extra == 'dev'
Requires-Dist: torch-pruning ~=1.3.6 ; extra == 'dev'
Requires-Dist: torchaudio ; extra == 'dev'
Requires-Dist: accelerate ; extra == 'dev'
Provides-Extra: diffusers
Requires-Dist: diffusers ~=0.25.1 ; extra == 'diffusers'
Requires-Dist: transformers ~=4.35.2 ; extra == 'diffusers'
Provides-Extra: timm
Requires-Dist: timm <=0.6.13 ; extra == 'timm'
